advarchs/__init__.py
advarchs/handlers.py
advarchs/utils.py
advarchs-0.1.7.dist-info/LICENSE
advarchs-0.1.7.dist-info/WHEEL
advarchs-0.1.7.dist-info/METADATA
advarchs-0.1.7.dist-info/RECORD
