Metadata-Version: 2.1
Name: advarchs
Version: 0.1.7
Summary: Data retrieval from remote archives
Home-page: https://github.com/elessarelfstone/advarchs
License: Apache-2.0
Keywords: archive,transfer,zip,rar,advarchs
Author: Dauren Sdykov
Author-email: elessarelfstone@mail.ru
Requires-Python: >=3.5,<4.0
Classifier: License :: OSI Approved :: Apache Software License
Classifier: Operating System :: Microsoft :: Windows
Classifier: Operating System :: POSIX :: Linux
Classifier: Programming Language :: Python :: 3
Classifier: Programming Language :: Python :: 3.5
Classifier: Programming Language :: Python :: 3.6
Classifier: Programming Language :: Python :: 3.7
Classifier: Topic :: System :: Archiving
Requires-Dist: requests (>=2.22,<3.0)
Requires-Dist: tomlkit (>=0.5.5,<0.6.0)
Project-URL: Repository, https://github.com/elessarelfstone/advarchs
